{
  "edition": "ja",
  "filed_at": "2026-07-21T06:00:00+09:00",
  "next_filing": "2026-07-21T21:00:00+00:00",
  "ai_assisted": true,
  "ai_reviewed": true,
  "ai_disclosure": "Grounded in real public data (weather via Open-Meteo, public holidays via Nager.Date) where available, phrased by AI (Gemini) and AI copy-reviewed against the saudade editorial rules. Written for this edition's readers — not translated from English. No human rewrite.",
  "cities": [
    {
      "city": "東京",
      "items": [
        {
          "n": "01",
          "headline": "東京都庭園美術館で、ルーシー・リーの静謐なうつわと向き合う。",
          "lede": "海の日が明け、街は日常の静けさを取り戻しつつある。",
          "body": "連休を終えた東京都庭園美術館では、ルーシー・リー展が静かな余韻を漂わせている。建築と工芸が織りなす空間は、都会の喧騒を忘れさせる。1 USDが162 JPYという為替相場の中、丁寧な暮らしの美学を再発見する時間は贅沢だ。アール・デコ様式の建物が、初夏の光を優しく受け止めている。美術館の庭を散策し、心地よい風を感じる午後を過ごしたい。",
          "source": "saudade desk",
          "source_date": "2026-07-21"
        },
        {
          "n": "02",
          "headline": "上野の森で、100年の歴史が刻む風景を見つめる。",
          "lede": "東京都美術館の開館100周年記念展が、この街の記憶を呼び起こす。",
          "body": "上野公園の一角で、この場所の風景をテーマにした展覧会が開かれている。開館100周年という節目は、街の変遷を静かに物語る。スタートアップ支援の動きなど、東京は常に新しい顔も見せている。リッツ・カールトン東京でニナ・メタイエが手掛ける花のスイーツも、今の東京の洗練を象徴する。街を歩けば、歴史と革新が交差する瞬間に立ち会える。",
          "source": "saudade desk",
          "source_date": "2026-07-21"
        },
        {
          "n": "03",
          "headline": "夏の午後は、美術館の余韻をカフェで味わう。",
          "lede": "パティシエの感性が、東京の夏に彩りを添える。",
          "body": "海の日を過ぎ、街には少しだけ余裕のある空気が流れている。ザ・リッツ・カールトン東京のカフェでは、ニナ・メタイエの美しいスイーツが提供されている。花をモチーフにした一皿は、食べるのが惜しいほどの完成度だ。1 USDが162 JPYの今、海外からの旅行者もこの繊細な味覚に驚きを隠さない。美術館での鑑賞後に、この特別なスイーツで一日を締めくくるのが今の東京流だ。",
          "source": "saudade desk",
          "source_date": "2026-07-21"
        }
      ]
    },
    {
      "city": "大阪",
      "items": [
        {
          "n": "01",
          "headline": "大阪の空は、26–34°Cの熱を帯びて澄み渡る。",
          "lede": "強い日差しが、街の活気を一段と際立たせる。",
          "body": "気温は26–34°Cまで上昇し、UV 8という強い日差しが降り注ぐ。屋外での活動は、こまめな休息を心がけたい。PM2.5は35で、空気は概ね安定している。19:08の夕暮れまで、街はエネルギーに満ちている。三連休の賑わいが去った後の大阪は、どこか穏やかな午後の表情を見せる。水分をとり、木陰で一息つく余裕を持ちたい。",
          "source": "saudade desk",
          "source_date": "2026-07-21"
        },
        {
          "n": "02",
          "headline": "大阪市立美術館で、水滸伝の英雄たちに触れる。",
          "lede": "開館90周年の記念特別展が、静かな知的好奇心を刺激する。",
          "body": "大阪市立美術館は開館90周年を迎え、水滸伝の特別展が開催中だ。連休中のイベントが終わり、館内は落ち着いた空気に包まれている。1 USDが162 JPYという相場は、海外の美術愛好家にとっても絶好の機会だ。歴史の重みを感じながら、館内の静寂を楽しむのがおすすめだ。日常の喧騒から離れ、物語の世界に深く浸る時間を大切にしたい。",
          "source": "saudade desk",
          "source_date": "2026-07-21"
        },
        {
          "n": "03",
          "headline": "夕暮れの街を歩き、19:08の光を待つ。",
          "lede": "三連休を終えた大阪は、少しだけ静けさを取り戻した。",
          "body": "海の日が過ぎ、街のイベントの余韻がわずかに残る。気温は34°Cに達するが、夕暮れには少しだけ涼しさが混じる。19:08の夕陽は、ビル街を黄金色に染め上げる。PM2.5の影響も少なく、視界は良好だ。連休中は多くの人で賑わったスタジアムやモールも、今は静かな日常の風景へと戻っている。街の移ろいを眺めるには、今が一番良い時期かもしれない。",
          "source": "saudade desk",
          "source_date": "2026-07-21"
        }
      ]
    },
    {
      "city": "京都",
      "items": [
        {
          "n": "01",
          "headline": "京都の空は、0.2mmの雨粒が微かに街を潤す。",
          "lede": "25–36°Cの湿った空気が、盆地特有の暑さを運ぶ。",
          "body": "気温は25–36°Cまで上がり、0.2mmの小雨が時折霧のように降る。UV 8の強い日差しと湿気が混ざり合う、京都らしい夏の一日だ。19:08には街が夜の帳に包まれる。1 USDが162 JPYの為替相場は、観光の際にも意識しておきたい。暑い時間帯は無理をせず、涼しい室内での鑑賞が心身を整える秘訣だ。",
          "source": "saudade desk",
          "source_date": "2026-07-21"
        },
        {
          "n": "02",
          "headline": "太秦映画村の夏祭りが、江戸の夜を彩り始める。",
          "lede": "歴史ある街並みが、夏の夜の舞台へと姿を変える。",
          "body": "太秦映画村では夏祭りが開催され、夜の街並みが幻想的な光に照らされる。海の日を過ぎても、京都の夏はこれからが本番だ。8月1日から始まる駅ビルウィークの準備も進んでいる。禅とジブリの展覧会への期待も高まり、街は文化的な高揚感に満ちている。162 JPYのレートで、京都の伝統と現代が織りなす贅沢な体験を味わいたい。",
          "source": "saudade desk",
          "source_date": "2026-07-21"
        },
        {
          "n": "03",
          "headline": "鴨川の風を待ちながら、京都の夜を慈しむ。",
          "lede": "19:08、夕暮れとともに街は少しだけ表情を変える。",
          "body": "気温は36°Cに達し、日中は厳しい暑さが続く。しかし、夕暮れ時になると鴨川沿いには心地よい風が吹き抜ける。0.2mmの雨が残した湿り気が、街の石畳を美しく反射させる。1 USDが162 JPYの今、京都の静かな隠れ家で過ごす時間は、何物にも代えがたい。街全体が祭りの気配を纏い、訪れる人々を優しく迎え入れている。",
          "source": "saudade desk",
          "source_date": "2026-07-21"
        }
      ]
    }
  ]
}
