{
  "track_or_image": "image",
  "id": "35380303",
  "title": "A close-up of a decorative golden teacup resting on a rustic stone surface outdoors.",
  "photographer": "Alexander Popadin",
  "photographer_url": "https://www.pexels.com/@irrabagon",
  "license": "Pexels-License",
  "license_url": "https://www.pexels.com/license/",
  "source": "Pexels",
  "source_url": "https://www.pexels.com/photo/vintage-golden-teacup-on-rustic-surface-35380303/",
  "city": "Seoul",
  "captured": null,
  "downloaded": "2026-05-06",
  "attribution_text": "Photo by Alexander Popadin on Pexels"
}
